Canoe_PY/__init__.py
Canoe_PY/core.py
Canoe_PY/exceptions.py
Canoe_PY/utils.py
canoe_py-0.1.1.dist-info/licenses/LICENSE
canoe_py-0.1.1.dist-info/METADATA
canoe_py-0.1.1.dist-info/WHEEL
canoe_py-0.1.1.dist-info/top_level.txt
canoe_py-0.1.1.dist-info/RECORD
