Metadata-Version: 2.4
Name: Canoe_PY
Version: 0.1.1
Summary: A custom library for interacting with Vector CANoe
Home-page: https://github.com/subhash37/Canoe_PY
Author: Subhashsingh Rajpurohit
Author-email: rajpurohits001@example.com
Project-URL: Bug Tracker, https://github.com/subhash37/Canoe_PY/issues
Classifier: Programming Language :: Python :: 3
Classifier: License :: OSI Approved :: MIT License
Classifier: Operating System :: Microsoft :: Windows
Classifier: Development Status :: 4 - Beta
Classifier: Intended Audience :: Developers
Classifier: Topic :: Software Development :: Libraries
Classifier: Topic :: Software Development :: Testing
Requires-Python: >=3.6
License-File: LICENSE
Requires-Dist: pywin32
Dynamic: author
Dynamic: author-email
Dynamic: classifier
Dynamic: description
Dynamic: description-content-type
Dynamic: home-page
Dynamic: license-file
Dynamic: project-url
Dynamic: requires-dist
Dynamic: requires-python
Dynamic: summary
